{
  "company": "RevLine Industries",
  "currency": "EUR",
  "units": "thousands",
  "scenarios": [
    {
      "id": 1,
      "title": "Launch & Ramp-Up",
      "narrative": "Baseline quarter with ramping production and startup inefficiencies.",
      "income_statement": {
        "gross_sales": 25000,
        "promo_allowances": 1200,
        "customer_allowances": 800,
        "net_sales": 23000,
        "materials_cost": 8500,
        "labor_cost": 4200,
        "overhead_cost": 2000,
        "total_cogs": 14700,
        "gross_profit": 8300,
        "marketing_expense": 900,
        "sga_expense": 2500,
        "depreciation": 400,
        "ebit": 4500,
        "interest_expense": 300,
        "net_income": 4200
      },
      "balance_sheet": {
        "cash": 5000,
        "accounts_receivable": 4200,
        "inventory_raw": 1800,
        "inventory_wip": 900,
        "inventory_fg": 2500,
        "total_inventory": 5200,
        "ppe": 12000,
        "total_assets": 21400,
        "accounts_payable": 3200,
        "current_debt": 1500,
        "total_debt": 7000,
        "equity": 11200,
        "total_liab_equity": 21400
      },
      "cash_flow": {
        "net_income": 4200,
        "change_working_capital": -1200,
        "capex": -400,
        "debt_activity": 0,
        "equity_activity": 0,
        "net_change_cash": 2600,
        "ending_cash": 7600
      },
      "teaching_flags": [
        "Observe WIP buildup vs finished goods transition",
        "Watch the impact of allowances on margin"
      ]
    }
  ]
}
